humu_download/__init__.py
humu_download/main.py
humu_download-1.1.5.dist-info/DESCRIPTION.rst
humu_download-1.1.5.dist-info/METADATA
humu_download-1.1.5.dist-info/RECORD
humu_download-1.1.5.dist-info/WHEEL
humu_download-1.1.5.dist-info/entry_points.txt
humu_download-1.1.5.dist-info/metadata.json
humu_download-1.1.5.dist-info/top_level.txt
