Metadata-Version: 2.0
Name: humu-download
Version: 1.1.5
Summary: CLI and curses UI for dowloading Humu data files
Home-page: https://github.com/humulabs/humu-download/blob/master/README.rst
Author: Michael Keirnan
Author-email: michael@keirnan.com
License: MIT
Keywords: arduino iot sd serial
Platform: any
Classifier: Development Status :: 4 - Beta
Classifier: Intended Audience :: Developers
Classifier: Intended Audience :: Science/Research
Classifier: Environment :: Console
Classifier: License :: OSI Approved :: MIT License
Classifier: Natural Language :: English
Classifier: Topic :: Internet
Classifier: Topic :: Software Development :: Libraries :: Python Modules
Classifier: Topic :: Scientific/Engineering
Classifier: Programming Language :: Python
Classifier: Programming Language :: Python :: 2
Classifier: Programming Language :: Python :: 2.7
Classifier: Programming Language :: Python :: 3
Classifier: Programming Language :: Python :: 3.4
Classifier: Programming Language :: Python :: 3.5
Requires-Dist: docopt
Requires-Dist: pandas
Requires-Dist: requests
Requires-Dist: urwid-timed-progress (>=1.1.1)
